{
  "plugins": [
    {
      "id": "github-dashboard",
      "name": "GitHub Dashboard",
      "description": "Monitor GitHub repositories and pull requests with real-time updates",
      "author": "Michael Gunderson",
      "category": "development-tools",
      "tags": [
        "github",
        "dashboard",
        "monitoring",
        "git",
        "repositories"
      ],
      "latest_version": "v1.0.0",
      "min_delve_version": "v0.1.0"
    }
  ],
  "total": 1,
  "last_updated": "2025-08-24T20:31:41.215935Z"
}